c3s_sm/__init__.py
c3s_sm/cli.py
c3s_sm/const.py
c3s_sm/download.py
c3s_sm/interface.py
c3s_sm/metadata.py
c3s_sm/misc.py
c3s_sm/reshuffle.py
c3s_sm-0.3.2.dist-info/AUTHORS.rst
c3s_sm-0.3.2.dist-info/LICENSE.txt
c3s_sm-0.3.2.dist-info/METADATA
c3s_sm-0.3.2.dist-info/WHEEL
c3s_sm-0.3.2.dist-info/entry_points.txt
c3s_sm-0.3.2.dist-info/top_level.txt
c3s_sm-0.3.2.dist-info/RECORD
