Metadata-Version: 2.1
Name: c3s_sm
Version: 0.3.2
Summary: Readers and utilities for working with C3S Soil Moisture data
Home-page: https://github.com/TUW-GEO/c3s_sm
Author: TU Wien
Author-email: support@qa4sm.eu
License: MIT
Project-URL: Documentation, https://c3s-sm.readthedocs.io/en/latest/
Platform: any
Classifier: Development Status :: 4 - Beta
Classifier: Programming Language :: Python
Requires-Python: >=3.6
License-File: LICENSE.txt
License-File: AUTHORS.rst
Requires-Dist: numpy
Requires-Dist: pandas
Requires-Dist: pygeobase
Requires-Dist: pyresample
Requires-Dist: netCDF4
Requires-Dist: xarray
Requires-Dist: pynetcf>=0.2.2
Requires-Dist: repurpose>=0.12
Requires-Dist: parse
Requires-Dist: cadati
Requires-Dist: smecv-grid>=0.3
Requires-Dist: more-itertools
Requires-Dist: click
Requires-Dist: cdsapi>=0.7.3
Requires-Dist: importlib-metadata; python_version < "3.8"
Provides-Extra: docs
Requires-Dist: matplotlib; extra == "docs"
Requires-Dist: jupyter; extra == "docs"
Requires-Dist: dask; extra == "docs"
Requires-Dist: sphinx<7; extra == "docs"
Requires-Dist: sphinx-rtd-theme; extra == "docs"
Requires-Dist: mock; extra == "docs"
Requires-Dist: pillow; extra == "docs"
Requires-Dist: recommonmark; extra == "docs"
Requires-Dist: readthedocs-sphinx-ext; extra == "docs"
Requires-Dist: myst-parser; extra == "docs"
Requires-Dist: nbsphinx; extra == "docs"
Provides-Extra: testing
Requires-Dist: pytest; extra == "testing"
Requires-Dist: pytest-cov; extra == "testing"
